README.md
setup.py
cluster_preflight_check/__init__.py
cluster_preflight_check/check.py
cluster_preflight_check/config.py
cluster_preflight_check/explain.py
cluster_preflight_check/main.py
cluster_preflight_check/pam.py
cluster_preflight_check/utils.py
cluster_preflight_check.egg-info/PKG-INFO
cluster_preflight_check.egg-info/SOURCES.txt
cluster_preflight_check.egg-info/dependency_links.txt
cluster_preflight_check.egg-info/entry_points.txt
cluster_preflight_check.egg-info/top_level.txt