Metadata-Version: 1.1
Name: cluster-preflight-check
Version: 0.0.32
Summary: Tool for Standardize Testing of Basic Cluster Functionality
Home-page: https://github.com/liangxin1300/cluster_preflight_check.git
Author: Xin Liang
Author-email: XLiang@suse.com
License: BSD
Platform: UNKNOWN
Classifier: Development Status :: 3 - Alpha
Classifier: Intended Audience :: System Administrators
Classifier: License :: OSI Approved :: BSD License
Classifier: Operating System :: POSIX
Classifier: Programming Language :: Python
Classifier: Programming Language :: Python :: 2
Classifier: Programming Language :: Python :: 2.6
Classifier: Programming Language :: Python :: 2.7
Classifier: Programming Language :: Python :: 3
Classifier: Programming Language :: Python :: 3.1
Classifier: Programming Language :: Python :: 3.2
Classifier: Programming Language :: Python :: 3.3
Classifier: Programming Language :: Python :: 3.4
Classifier: Programming Language :: Python :: 3.5
Classifier: Programming Language :: Python :: 3.6
Classifier: Topic :: Software Development :: Libraries :: Python Modules
Classifier: Topic :: System :: Clustering
Classifier: Topic :: System :: Networking
Classifier: Topic :: System :: Systems Administration
